talkingheads/__init__.py
talkingheads/base_browser.py
talkingheads/object_map.py
talkingheads/utils.py
talkingheads/model_library/__init__.py
talkingheads/model_library/chatgpt.py
talkingheads/model_library/claude.py
talkingheads/model_library/copilot.py
talkingheads/model_library/gemini.py
talkingheads/model_library/huggingchat.py
talkingheads/model_library/lechat.py
talkingheads/model_library/pi.py
talkingheads/multiagent/__init__.py
talkingheads/multiagent/multiagent.py
talkingheads-0.5.4.dist-info/LICENSE
talkingheads-0.5.4.dist-info/METADATA
talkingheads-0.5.4.dist-info/WHEEL
talkingheads-0.5.4.dist-info/top_level.txt
talkingheads-0.5.4.dist-info/RECORD
