Metadata-Version: 2.1
Name: talkingheads
Version: 0.5.4
Summary: A library to communicate with AI assistants such as ChatGPT, Claude, Copilot, Gemini, HuggingChat, and Pi, and enabling multiagent interactions between them.
Author-email: Ugur Sahin <ugorsahin@tutanota.de>
Project-URL: Source, https://github.com/ugorsahin/TalkingHeads
Classifier: Programming Language :: Python :: 3
Classifier: Operating System :: OS Independent
Requires-Python: >=3.8
License-File: LICENSE
Requires-Dist: selenium >=4.10.0
Requires-Dist: undetected-chromedriver >=3.5.3
Requires-Dist: pandas >=2.0.0
Requires-Dist: easydict
Requires-Dist: validators >=0.22.0
Requires-Dist: filetype >=1.2.0
Requires-Dist: emoji >=2.10.1
Requires-Dist: PyYAML >6.0
Requires-Dist: mergedeep >=1.3.4
